condorpy/__init__.py
condorpy/exceptions.py
condorpy/htcondor_object_base.py
condorpy/job.py
condorpy/logger.py
condorpy/node.py
condorpy/remote_utils.py
condorpy/static.py
condorpy/templates.py
condorpy/workflow.py
tests/__init__.py
tests/test_integraiton.py
tests/test_job.py
tests/test_node.py
tests/test_templates.py
tests/test_workflow.py
condorpy-0.6.0.dist-info/LICENSE
condorpy-0.6.0.dist-info/METADATA
condorpy-0.6.0.dist-info/WHEEL
condorpy-0.6.0.dist-info/top_level.txt
condorpy-0.6.0.dist-info/RECORD
