Metadata-Version: 2.1
Name: condorpy
Version: 0.6.0
Summary: A Python wrapper for HTCondor's cli
Home-page: http://tethysplatform.org/condorpy/
Author: Scott Christensen
Author-email: sdc50@byu.net
License: BSD 2-Clause License
Keywords: htcondor distributed-computing job-scheduling
Platform: UNKNOWN
License-File: LICENSE
Requires-Dist: scp
Requires-Dist: paramiko
